pds4_tools/__about__.py
pds4_tools/__init__.py
pds4_tools/extern/__init__.py
pds4_tools/extern/appdirs.py
pds4_tools/extern/argparse.py
pds4_tools/extern/cached_property.py
pds4_tools/extern/ordered_dict.py
pds4_tools/extern/six.py
pds4_tools/extern/zscale.py
pds4_tools/reader/__init__.py
pds4_tools/reader/array_objects.py
pds4_tools/reader/core.py
pds4_tools/reader/data.py
pds4_tools/reader/data_types.py
pds4_tools/reader/general_objects.py
pds4_tools/reader/header_objects.py
pds4_tools/reader/label_objects.py
pds4_tools/reader/read_arrays.py
pds4_tools/reader/read_headers.py
pds4_tools/reader/read_label.py
pds4_tools/reader/read_tables.py
pds4_tools/reader/table_objects.py
pds4_tools/utils/__init__.py
pds4_tools/utils/compat.py
pds4_tools/utils/constants.py
pds4_tools/utils/data_access.py
pds4_tools/utils/deprecation.py
pds4_tools/utils/exceptions.py
pds4_tools/utils/helpers.py
pds4_tools/utils/logging.py
pds4_tools/viewer/__init__.py
pds4_tools/viewer/cache.py
pds4_tools/viewer/core.py
pds4_tools/viewer/header_view.py
pds4_tools/viewer/image_view.py
pds4_tools/viewer/label_view.py
pds4_tools/viewer/mpl.py
pds4_tools/viewer/plot_view.py
pds4_tools/viewer/summary_view.py
pds4_tools/viewer/table_view.py
pds4_tools/viewer/logo/logo.gif
pds4_tools/viewer/logo/logo.icns
pds4_tools/viewer/logo/logo.ico
pds4_tools/viewer/widgets/__init__.py
pds4_tools/viewer/widgets/notebook.py
pds4_tools/viewer/widgets/scrolled_frame.py
pds4_tools/viewer/widgets/tooltip.py
pds4_tools/viewer/widgets/tree.py
pds4_tools-1.3.dist-info/LICENSES
pds4_tools-1.3.dist-info/METADATA
pds4_tools-1.3.dist-info/WHEEL
pds4_tools-1.3.dist-info/top_level.txt
pds4_tools-1.3.dist-info/RECORD
