Metadata-Version: 2.1
Name: pds4-tools
Version: 1.3
Summary: Package to read and display NASA PDS4 data
Home-page: https://sbnwiki.astro.umd.edu/wiki/Python_PDS4_Tools
Author: Lev Nagdimunov
Author-email: lnagdi1@astro.umd.edu
License: BSD
Keywords: pds4_viewer,pds4,pds
Platform: UNKNOWN
Classifier: Development Status :: 5 - Production/Stable
Classifier: Intended Audience :: Science/Research
Classifier: Intended Audience :: Developers
Classifier: Topic :: Scientific/Engineering :: Astronomy
Classifier: Topic :: Scientific/Engineering :: Physics
Classifier: License :: OSI Approved :: BSD License
Classifier: Operating System :: Microsoft :: Windows
Classifier: Operating System :: POSIX
Classifier: Operating System :: Unix
Classifier: Operating System :: MacOS
Classifier: Programming Language :: Python :: 2
Classifier: Programming Language :: Python :: 2.6
Classifier: Programming Language :: Python :: 2.7
Classifier: Programming Language :: Python :: 3
Classifier: Programming Language :: Python :: 3.3
Classifier: Programming Language :: Python :: 3.4
Classifier: Programming Language :: Python :: 3.5
Classifier: Programming Language :: Python :: 3.6
Classifier: Programming Language :: Python :: 3.7
Classifier: Programming Language :: Python :: 3.8
Classifier: Programming Language :: Python :: 3.9
Requires-Dist: numpy
Provides-Extra: tests
Requires-Dist: pytest ; extra == 'tests'
Provides-Extra: viewer
Requires-Dist: matplotlib ; extra == 'viewer'
Requires-Dist: Tkinter ; extra == 'viewer'
